{
  "operationalLayers": [
    {
      "id": "CountyBoundaries",
      "layerType": "ArcGISTiledMapServiceLayer",
      "url": "http://data.wsdot.wa.gov/arcgis/rest/services/Shared/CountyBoundaries/MapServer",
      "visibility": false,
      "opacity": 1,
      "title": "County Boundaries"
    },
    {
      "id": "LegislativeDistricts",
      "layerType": "ArcGISMapServiceLayer",
      "url": "http://data.wsdot.wa.gov/arcgis/rest/services/Shared/LegislativeDistricts/MapServer",
      "visibility": false,
      "opacity": 1,
      "title": "Legislative Districts"
    },
    {
      "id": "CityLimits",
      "layerType": "ArcGISMapServiceLayer",
      "url": "http://data.wsdot.wa.gov/arcgis/rest/services/Shared/CityLimits/MapServer",
      "visibility": false,
      "opacity": 0.52,
      "title": "City Limits",
      "layers": [
        {
          "id": 0,
          "layerDefinition": {
            "source": {
              "type": "mapLayer",
              "mapLayerId": 0
            }
          },
          "name": "Cities",
          "minScale": 1500000,
          "maxScale": 750001,
          "parentLayerId": -1,
          "defaultVisibility": true
        },
        {
          "id": 1,
          "layerDefinition": {
            "source": {
              "type": "mapLayer",
              "mapLayerId": 1
            }
          },
          "name": "Major Cities",
          "minScale": 0,
          "maxScale": 1500001,
          "parentLayerId": -1,
          "defaultVisibility": true
        },
        {
          "id": 2,
          "layerDefinition": {
            "source": {
              "type": "mapLayer",
              "mapLayerId": 2
            },
            "drawingInfo": {
              "renderer": {
                "type": "simple",
                "label": "",
                "description": "",
                "symbol": {
                  "color": [
                    227,
                    139,
                    79,
                    255
                  ],
                  "outline": {
                    "color": [
                      128,
                      128,
                      128,
                      255
                    ],
                    "width": 0.4,
                    "type": "esriSLS",
                    "style": "esriSLSSolid"
                  },
                  "type": "esriSFS",
                  "style": "esriSFSSolid"
                }
              }
            }
          },
          "name": "Incorporated City Boundaries",
          "minScale": 581848,
          "maxScale": 9027,
          "parentLayerId": -1,
          "defaultVisibility": true
        }
      ]
    },
    {
      "id": "RegionalTransportationPlanning",
      "layerType": "ArcGISMapServiceLayer",
      "url": "http://data.wsdot.wa.gov/arcgis/rest/services/Shared/RegionalTransportationPlanning/MapServer",
      "visibility": false,
      "opacity": 1,
      "title": "Regional Transportation Planning Organization"
    },
    {
      "id": "RegionBoundaries",
      "layerType": "ArcGISTiledMapServiceLayer",
      "url": "http://data.wsdot.wa.gov/arcgis/rest/services/Shared/RegionBoundaries/MapServer",
      "visibility": false,
      "opacity": 1,
      "title": "Region Boundaries"
    },
    {
      "id": "SixYearPlan",
      "layerType": "ArcGISMapServiceLayer",
      "url": "http://hqolymgis98d:6080/arcgis/rest/services/TransportationProjects/SixYearPlan/MapServer",
      "visibility": true,
      "opacity": 1,
      "title": "WSDOT Projects (6 Year Plan)",
      "layers": [
        {
          "id": 0,
          "popupInfo": {
            "title": "{PIN} - {Project_Title}",
            "fieldInfos": [
              {
                "fieldName": "OBJECTID",
                "label": "OBJECTID",
                "tooltip": "",
                "visible": false,
                "stringFieldOption": "textbox"
              },
              {
                "fieldName": "PIN",
                "label": "Project Number",
                "tooltip": "",
                "visible": true,
                "stringFieldOption": "textbox"
              },
              {
                "fieldName": "Project_Title",
                "label": "Project Title",
                "tooltip": "",
                "visible": true,
                "stringFieldOption": "textbox"
              },
              {
                "fieldName": "Region",
                "label": "Region",
                "tooltip": "",
                "visible": true,
                "stringFieldOption": "textbox"
              },
              {
                "fieldName": "Improvement_Type",
                "label": "Improvement Type",
                "tooltip": "",
                "visible": true,
                "stringFieldOption": "textbox"
              },
              {
                "fieldName": "Program",
                "label": "Program",
                "tooltip": "",
                "visible": true,
                "stringFieldOption": "textbox"
              },
              {
                "fieldName": "Sub_Program",
                "label": "Sub Program",
                "tooltip": "",
                "visible": true,
                "stringFieldOption": "textbox"
              },
              {
                "fieldName": "Work_Description",
                "label": "Work Description",
                "tooltip": "",
                "visible": true,
                "stringFieldOption": "textbox"
              },
              {
                "fieldName": "PE_Start_Date",
                "label": "Preliminary Engineering Start",
                "tooltip": "",
                "visible": true,
                "format": {
                  "dateFormat": "longMonthDayYear"
                },
                "stringFieldOption": "textbox"
              },
              {
                "fieldName": "Ad_Date",
                "label": "Advertisement",
                "tooltip": "",
                "visible": true,
                "format": {
                  "dateFormat": "longMonthDayYear"
                },
                "stringFieldOption": "textbox"
              },
              {
                "fieldName": "OC_Date",
                "label": "Operationally Complete",
                "tooltip": "",
                "visible": true,
                "format": {
                  "dateFormat": "longMonthDayYear"
                },
                "stringFieldOption": "textbox"
              },
              {
                "fieldName": "Revenue_Package",
                "label": "Revenue Package",
                "tooltip": "",
                "visible": true,
                "stringFieldOption": "textbox"
              },
              {
                "fieldName": "Funding_Source",
                "label": "Funding Source",
                "tooltip": "",
                "visible": true,
                "stringFieldOption": "textbox"
              },
              {
                "fieldName": "Congressional_District",
                "label": "Congressional District",
                "tooltip": "",
                "visible": true,
                "stringFieldOption": "textbox"
              },
              {
                "fieldName": "Legislative_District",
                "label": "Legislative District",
                "tooltip": "",
                "visible": true,
                "stringFieldOption": "textbox"
              },
              {
                "fieldName": "County",
                "label": "County",
                "tooltip": "",
                "visible": true,
                "stringFieldOption": "textbox"
              },
              {
                "fieldName": "Route",
                "label": "Route",
                "tooltip": "",
                "visible": true,
                "stringFieldOption": "textbox"
              },
              {
                "fieldName": "Begin_Mile_Post",
                "label": "Begin Mile Post",
                "tooltip": "",
                "visible": true,
                "format": {
                  "places": 2,
                  "digitSeparator": true
                },
                "stringFieldOption": "textbox"
              },
              {
                "fieldName": "End_Mile_Post",
                "label": "End Mile Post",
                "tooltip": "",
                "visible": true,
                "format": {
                  "places": 2,
                  "digitSeparator": true
                },
                "stringFieldOption": "textbox"
              },
              {
                "fieldName": "Shape",
                "label": "Shape",
                "tooltip": "",
                "visible": false,
                "stringFieldOption": "textbox"
              },
              {
                "fieldName": "LRS_Date",
                "label": "SRMP Date",
                "tooltip": "",
                "visible": false,
                "stringFieldOption": "textbox"
              }
            ],
            "description": null,
            "showAttachments": true,
            "mediaInfos": []
          }
        }
      ]
    },
    {
      "id": "MilepostValues",
      "layerType": "ArcGISMapServiceLayer",
      "url": "http://www.wsdot.wa.gov/geosvcs/ArcGIS/rest/services/Shared/MilepostValues/MapServer",
      "visibility": true,
      "opacity": 1,
      "title": "Milepost Values",
      "itemId": "03ec5ff3609f45caa849d5afa4d92e9e"
    }
  ],
  "baseMap": {
    "baseMapLayers": [
      {
        "id": "wsdotbasemap",
        "layerType": "ArcGISTiledMapServiceLayer",
        "opacity": 1,
        "visibility": true,
        "url": "http://www.wsdot.wa.gov/geosvcs/ArcGIS/rest/services/Shared/WebBaseMapWebMercator/MapServer"
      }
    ],
    "title": "WSDOT Basemap"
  },
  "spatialReference": {
    "wkid": 102100
  },
  "authoringApp": "WebMapViewer",
  "authoringAppVersion": "3.10",
  "version": "2.3",
  "applicationProperties": {
    "viewing": {
      "routing": {
        "enabled": true
      },
      "measure": {
        "enabled": true
      },
      "basemapGallery": {
        "enabled": true
      },
      "search": {
        "enabled": true,
        "disablePlaceFinder": false,
        "hintText": "Place or Address",
        "layers": []
      }
    }
  }
}